buguet/__init__.py
buguet/cli.py
buguet/contract_data_loader.py
buguet/debugger.py
buguet/models.py
buguet/parser.py
buguet/repl.py
buguet/tracer.py
buguet/util.py
buguet-1.0.3.dist-info/LICENSE
buguet-1.0.3.dist-info/METADATA
buguet-1.0.3.dist-info/WHEEL
buguet-1.0.3.dist-info/entry_points.txt
buguet-1.0.3.dist-info/top_level.txt
buguet-1.0.3.dist-info/RECORD
