Metadata-Version: 2.1
Name: buguet
Version: 1.0.3
Summary: Ethereum debugger
Home-page: https://github.com/dr6kl/buguet
Author: dr6kl
Author-email: dr6kl@protonmail.com
License: GPL
Platform: UNKNOWN
Classifier: Programming Language :: Python :: 3
Classifier: Operating System :: OS Independent
Requires-Dist: web3 (<5,>=4.7.2)
Requires-Dist: pysha3 (<2,>=1.0.2)
Requires-Dist: termcolor (<2,>=1.1.0)
